blister_cpp/__init__.py
blister_cpp/compile_commands.py
blister_cpp/config.py
blister_cpp/ninja.py
blister_cpp/outputs.py
blister_cpp/sources.py
blister_cpp/timing.py
blister_cpp/templates/__init__.py
blister_cpp/templates/infoplist.py
blister_cpp/templates/preamble.py
blister_cpp-0.0.1.data/scripts/bli
blister_cpp-0.0.1.dist-info/LICENSE
blister_cpp-0.0.1.dist-info/METADATA
blister_cpp-0.0.1.dist-info/WHEEL
blister_cpp-0.0.1.dist-info/top_level.txt
blister_cpp-0.0.1.dist-info/RECORD
