Metadata-Version: 2.1
Name: blister-cpp
Version: 0.0.1
Summary: Conventions-over-configuration C++/modules project manager.
Home-page: https://github.com/m4c0/blister
Author: Eduardo Costa
Author-email: m4c0@users.noreply.github.com
License: UNKNOWN
Platform: UNKNOWN
Classifier: Development Status :: 2 - Pre-Alpha
Classifier: Intended Audience :: Developers
Classifier: Programming Language :: Python :: 3
Classifier: License :: OSI Approved :: GNU General Public License v3 (GPLv3)
Classifier: Operating System :: MacOS :: MacOS X
Requires-Python: >=3.6
Requires-Dist: PyYAML (>=5.1.2)
